{"createdAt":"2025-10-13T12:50:45.750Z","id":"1bOzJtJ0ktYkXoiA","name":"Envio de mensagens com documento","active":false,"isArchived":false,"nodes":[{"parameters":{"options":{}},"type":"n8n-nodes-base.splitInBatches","typeVersion":3,"position":[0,0],"id":"83f68a24-4346-43d1-a60e-9f874dfb7ee3","name":"Loop Over Items8"},{"parameters":{"amount":10},"type":"n8n-nodes-base.wait","typeVersion":1.1,"position":[512,16],"id":"386bed6e-c867-4a6f-9bf4-5918b9d0012c","name":"Wait8","webhookId":"35732a36-53f9-4363-b0f3-6a4430104193"},{"parameters":{"resource":"messages-api","operation":"send-document","instanceName":"Financeiro","remoteJid":"={{ $json.telefone }}","media":"={{ $json.data }}","caption":"={{ $json.caption }}","fileName":"BOLETO CASTELO BRANCO CONTABILIDADE.pdf","options_message":{}},"type":"n8n-nodes-evolution-api.evolutionApi","typeVersion":1,"position":[288,16],"id":"95faa787-75ef-4dfb-ace2-62fd3dac3448","name":"Evolution API5","onError":"[REDACTED]"},{"parameters":{"inputSource":"passthrough"},"type":"[REDACTED]","typeVersion":1.1,"position":[-208,0],"id":"4470963a-4faf-4929-aa98-3bc0bed82f3e","name":"When Executed by Another Workflow"}],"connections":{"Loop Over Items8":{"main":[[],[{"node":"Evolution API5","type":"main","index":0}]]},"Wait8":{"main":[[{"node":"Loop Over Items8","type":"main","index":0}]]},"Evolution API5":{"main":[[{"node":"Wait8","type":"main","index":0}]]},"When Executed by Another Workflow":{"main":[[{"node":"Loop Over Items8","type":"main","index":0}]]}}}