{"createdAt":"2025-10-15T18:02:11.261Z","id":"iWO2Wnb76XTr108l","name":"Recupera Link","active":false,"isArchived":false,"nodes":[{"parameters":{"workflowInputs":{"values":[{"name":"id"}]}},"type":"[REDACTED]","typeVersion":1.1,"position":[0,0],"id":"f0f6d11c-16b2-4d39-b4ed-120a49f2699e","name":"When Executed by Another Workflow"},{"parameters":{"url":"[REDACTED]","authentication":"[REDACTED]","options":{}},"type":"n8n-nodes-base.httpRequest","typeVersion":4.2,"position":[208,0],"id":"3103dcec-fa17-4faa-8a52-b372993fa9e7","name":"HTTP Request","onError":"[REDACTED]"},{"parameters":{"options":{}},"type":"n8n-nodes-base.removeDuplicates","typeVersion":2,"position":[688,0],"id":"3d52352a-9445-49bd-bd8c-8b7dba5dce2d","name":"Remove Duplicates"},{"parameters":{"jsCode":"const items = $input.all();\n\nreturn items.map(item => {\n  const parents = item.json.parents;\n  // item.json.parentsArray = typeof parents === 'string'\n  //   ? parents.split(',').map(p => p.trim())\n  //   : parents;\n  return item;\n});\n"},"type":"n8n-nodes-base.code","typeVersion":2,"position":[416,0],"id":"cd6c4b19-578c-4676-bb0f-174300c84e54","name":"Code in JavaScript"}],"connections":{"When Executed by Another Workflow":{"main":[[{"node":"HTTP Request","type":"main","index":0}]]},"HTTP Request":{"main":[[{"node":"Code in JavaScript","type":"main","index":0}]]},"Code in JavaScript":{"main":[[{"node":"Remove Duplicates","type":"main","index":0}]]}}}